<?xml version="1.0" encoding="utf-8"?>
<resources>

    <string-array name="pref_connected_have_notif_reminder_repeat_interval">
        <item>3 minutes</item>
        <item>5 minutes</item>
        <item>10 minutes</item>
        <item>15 minutes</item>
        <item>20 minutes</item>
        <item>30 minutes</item>
        <item>1 heure</item>
        <item>2 heures</item>
        <item>3 heures</item>
    </string-array>

    <string-array name="notification_group_repeat">
        <item>Toujours</item>
        <item>Jamais</item>
        <item>Une fois que</item>
        <item>Deux fois</item>
        <item>Trois fois</item>
    </string-array>

    <string-array name="notification_group_grouped_dispay">
        <item>Show all when the device is connecting, otherwise only the latest notification</item>
        <item>Show all notifications</item>
        <item>Show only the latest notification</item>
    </string-array>

    <string-array name="notification_group_grouped_order">
        <item>In normal order</item>
        <item>In reverse order</item>
    </string-array>

    <string-array name="notification_group_display_time">
        <item>Auto (3 – 5 secondes)</item>
        <item>3 secondes</item>
        <item>4 secondes</item>
        <item>5 secondes</item>
        <item>6 secondes</item>
        <item>7 secondes</item>
    </string-array>

    <string-array name="call_button_action">
        <item>Appels rejetés, terminés</item>
        <item>Appels basculés en muet</item>
        <item>Appels décrochés</item>
    </string-array>

    <string-array name="pref_distance_unit">
        <item>Métrique (kilomètre)</item>
        <item>Impériales (mile)</item>
    </string-array>

    <string-array name="touch_mute_toggle_ringer_mode">
        <item>Vibration</item>
        <item>Muet</item>
        <item>Ne pas déranger (priorité uniquement)</item>
        <item>Ne pas déranger (alarmes uniquement)</item>
        <item>Ne pas déranger (aucune interruption)</item>
    </string-array>


    <string-array name="pref_theme_day_night">
        <item>Par défaut</item>
        <item>Brillant</item>
        <item>Sombre</item>
    </string-array>

    <string-array name="workout">
        <item>Unknown</item>
        <item>Running</item>
        <item>Treadmill</item>
        <item>Walking</item>
        <item>Cycling</item>
        <item>Hiking</item>
        <item>Spinning</item>
        <item>Yoga</item>
        <item>Training</item>
        <item>Gymnastics</item>
        <item>Basketball</item>
        <item>Football</item>
        <item>Rowing</item>
        <item>Jump rope</item>
        <item>Tennis</item>
        <item>Baseball</item>
        <item>Badminton</item>
        <item>Rugby</item>
        <item>Table tennis</item>
        <item>Indoor swimming</item>
        <item>Outdoor swimming</item>
        <item>Sit up</item>
    </string-array>

</resources>